.travis.yml
NOTICE.txt
README.rst
bootstrap.py
buildout.cfg
eke.labcas.sublime-project
setup.cfg
setup.py
travis.cfg
docs/HISTORY.txt
docs/INSTALL.txt
docs/LICENSE.txt
src/eke/__init__.py
src/eke.labcas.egg-info/PKG-INFO
src/eke.labcas.egg-info/SOURCES.txt
src/eke.labcas.egg-info/dependency_links.txt
src/eke.labcas.egg-info/entry_points.txt
src/eke.labcas.egg-info/namespace_packages.txt
src/eke.labcas.egg-info/not-zip-safe
src/eke.labcas.egg-info/requires.txt
src/eke.labcas.egg-info/top_level.txt
src/eke/labcas/README.rst
src/eke/labcas/__init__.py
src/eke/labcas/configure.zcml
src/eke/labcas/labcasdataset.py
src/eke/labcas/labcasfolder.py
src/eke/labcas/testing.py
src/eke/labcas/upgrades.py
src/eke/labcas/upgrades.zcml
src/eke/labcas/labcasfolder_templates/labcasfolderrdfingestor.pt
src/eke/labcas/profiles/default/metadata.xml
src/eke/labcas/profiles/default/types.xml
src/eke/labcas/profiles/default/types/eke.labcas.labcasdataset.xml
src/eke/labcas/profiles/default/types/eke.labcas.labcasfolder.xml
src/eke/labcas/static/beaker.png
src/eke/labcas/static/test-tubes.png
src/eke/labcas/tests/__init__.py
src/eke/labcas/tests/test_functional.py
src/eke/labcas/tests/test_setup.py
src/eke/labcas/tests/data/example.rdf