Metadata-Version: 2.1
Name: eke.labcas
Version: 0.0.3
Summary: Laboratory Catalog and Archive Service for the EDRN Knowledge Environment
Home-page: https://github.com/EDRN/eke.labcas
Author: Sean Kelly
Author-email: sean.kelly@jpl.nasa.gov
Maintainer: Sean Kelly
Maintainer-email: sean.kelly@jpl.nasa.gov
License: ALv2
Keywords: web zope plone edrn cancer biomarkers eke knowledge cas labcas laboratory
Platform: UNKNOWN
Classifier: Development Status :: 3 - Alpha
Classifier: Environment :: Web Environment
Classifier: Framework :: Plone
Classifier: Intended Audience :: Healthcare Industry
Classifier: Intended Audience :: Science/Research
Classifier: License :: OSI Approved :: Apache Software License
Classifier: Operating System :: OS Independent
Classifier: Programming Language :: Python
Classifier: Topic :: Internet :: WWW/HTTP
Classifier: Topic :: Scientific/Engineering :: Bio-Informatics
Classifier: Topic :: Software Development :: Libraries :: Python Modules
Provides-Extra: test
